nexus_pcv/__init__.py
nexus_pcv/__main__.py
nexus_pcv/apic.py
nexus_pcv/cli/__init__.py
nexus_pcv/cli/main.py
nexus_pcv/cli/options.py
nexus_pcv/const.py
nexus_pcv/ndi.py
nexus_pcv/pcv.py
nexus_pcv-0.2.1.dist-info/LICENSE
nexus_pcv-0.2.1.dist-info/METADATA
nexus_pcv-0.2.1.dist-info/WHEEL
nexus_pcv-0.2.1.dist-info/entry_points.txt
nexus_pcv-0.2.1.dist-info/RECORD
