Metadata-Version: 2.3
Name: nexus-pcv
Version: 0.2.1
Summary: A CLI tool to perform a pre-change validation on Nexus Dashboard Insights or Network Assurance Engine.
License: LICENSE
Author: Daniel Schmidt
Author-email: danischm@cisco.com
Maintainer: Daniel Schmidt
Maintainer-email: danischm@cisco.com
Requires-Python: >=3.8,<4.0
Classifier: License :: Other/Proprietary License
Classifier: Programming Language :: Python :: 3
Classifier: Programming Language :: Python :: 3.8
Classifier: Programming Language :: Python :: 3.9
Classifier: Programming Language :: Python :: 3.10
Classifier: Programming Language :: Python :: 3.11
Classifier: Programming Language :: Python :: 3.12
Classifier: Programming Language :: Python :: 3.13
Requires-Dist: click (>=8.1.3,<9.0.0)
Requires-Dist: errorhandler (>=2.0.1,<3.0.0)
Requires-Dist: pyyaml (>=6.0,<7.0)
Requires-Dist: requests (>=2.28.1,<3.0.0)
Project-URL: Documentation, https://github.com/netascode/nexus-pcv
Project-URL: Homepage, https://github.com/netascode/nexus-pcv
Project-URL: Repository, https://github.com/netascode/nexus-pcv
